setup.py
tests/__init__.py
tests/test_scraper.py
twitprof/__init__.py
twitprof/api.py
twitprof/models.py
twitprof/scraper.py
twitprof/test_scraper.py
twitprof.egg-info/PKG-INFO
twitprof.egg-info/SOURCES.txt
twitprof.egg-info/dependency_links.txt
twitprof.egg-info/requires.txt
twitprof.egg-info/top_level.txt
twitprof/tasks/__init__.py
twitprof/tasks/celery.py
twitprof/tasks/tasks.py