Metadata-Version: 1.0
Name: twitprof
Version: 0.4.1
Summary: Twitter Profile Scraper
Home-page: https://github.com/santiavenda2/twitter-scrapper
Author: Santiago Avendaño
Author-email: santiavenda2@gmail.com
License: Apache License
Platform: UNKNOWN
